src/__init__.py
src/_auth.py
src/_client.py
src/_settings.py
src/_types.py
src/server.py
src/tools.py
src/version.py
smx_mcp-0.1.0.dist-info/METADATA
smx_mcp-0.1.0.dist-info/WHEEL
smx_mcp-0.1.0.dist-info/entry_points.txt
smx_mcp-0.1.0.dist-info/licenses/LICENSE
smx_mcp-0.1.0.dist-info/RECORD
