Metadata-Version: 2.4
Name: smx-mcp
Version: 0.1.0
Summary: MCP server for interacting with Standard Metrics
Author-email: Standard Metrics <info@standardmetrics.io>
License-File: LICENSE
Requires-Python: >=3.13
Requires-Dist: aiohttp>=3.12.12
Requires-Dist: fastmcp>=2.8.0
Requires-Dist: pydantic-settings>=2.9.1
Requires-Dist: pydantic>=2.11.5
